MANIFEST.in
README.rst
setup.py
aliyun_python_sdk_jaq.egg-info/PKG-INFO
aliyun_python_sdk_jaq.egg-info/SOURCES.txt
aliyun_python_sdk_jaq.egg-info/dependency_links.txt
aliyun_python_sdk_jaq.egg-info/requires.txt
aliyun_python_sdk_jaq.egg-info/top_level.txt
aliyunsdkjaq/__init__.py
aliyunsdkjaq/request/__init__.py
aliyunsdkjaq/request/v20160412/BatchScanMalwareRequest.py
aliyunsdkjaq/request/v20160412/BatchScanPluginRequest.py
aliyunsdkjaq/request/v20160412/DiyShieldRequest.py
aliyunsdkjaq/request/v20160412/GetRiskDetail4BatchRequest.py
aliyunsdkjaq/request/v20160412/GetRiskDetailRequest.py
aliyunsdkjaq/request/v20160412/GetRiskSummaryRequest.py
aliyunsdkjaq/request/v20160412/GetShieldResultRequest.py
aliyunsdkjaq/request/v20160412/ScanFakeRequest.py
aliyunsdkjaq/request/v20160412/ScanMalwareRequest.py
aliyunsdkjaq/request/v20160412/ScanVulnRequest.py
aliyunsdkjaq/request/v20160412/ShieldRequest.py
aliyunsdkjaq/request/v20160412/__init__.py